{
	"characters": [
		{
			"name": "Jon Snow",
			"shortCode": "johnsnow",
			"actor": "Kit Harrington",
			"house": "Stark",
			"location": "The Wall"
		},
		{
			"name": "Tyrion Lannister",
			"shortCode": "tyrion",
			"actor": "Peter Dinklage",
			"house": "Lannister",
      		"location": ""
		},
		{
			"name": "Brienne of Tarth",
			"shortCode": "brienne",
			"actor": "Gwendoline Christie",
			"house": "Clegane",
			"location": ""
		},
		{
			"name": "Eddard Stark",
			"shortCode": "ned-stark",
			"actor": "Sean Bean",
			"house": "Stark",
			"location": ""
		},
		{
			"name": "Sandor Clegane",
			"shortCode": "the-hound",
			"actor": "Rory McCann",
			"house": "Clegane",
			"location": "unknown"
		},
    {
			"name": "Daenerys Targaryen",
			"shortCode": "daenerys",
			"actor": "Emilia Clarke",
			"house": "Targaryen",
			"location": "Mereen"
		}
	]
}